snomed_ct/__init__.py
snomed_ct/controlled_natural_language.py
snomed_ct/exceptions.py
snomed_ct/manager.py
snomed_ct/models.py
snomed_ct/testing.py
snomed_ct/management/__init__.py
snomed_ct/management/commands/__init__.py
snomed_ct/management/commands/create_namespace_counter.py
snomed_ct/management/commands/create_snomed_ct_module.py
snomed_ct/management/commands/create_snomed_ct_reference_set.py
snomed_ct/management/commands/load_snomed_ct_data.py
snomed_ct/management/commands/query_snomed_ct_data.py
snomed_ct/migrations/0001_initial.py
snomed_ct/migrations/0002_auto_20230612_2035.py
snomed_ct/migrations/__init__.py
django_snomed_ct-0.5.1.dist-info/LICENSE
django_snomed_ct-0.5.1.dist-info/METADATA
django_snomed_ct-0.5.1.dist-info/WHEEL
django_snomed_ct-0.5.1.dist-info/top_level.txt
django_snomed_ct-0.5.1.dist-info/RECORD
