Metadata-Version: 2.1
Name: django-snomed-ct
Version: 0.5.1
Summary: A Django App for storing, managing, and querying SNOMED CT by itself or as part of a Django application.
Author-email: Chimezie Ogbuji <chimezie@gmail.com>
License: GNU GENERAL PUBLIC LICENSE
Classifier: Development Status :: 4 - Beta
Classifier: Programming Language :: Python
Classifier: Programming Language :: Python :: 3.10
Classifier: Programming Language :: Python :: 3.11
Classifier: Programming Language :: Python :: Implementation :: PyPy
Requires-Python: >=3.10
License-File: LICENSE
Requires-Dist: openai
Requires-Dist: python-dotenv
